py_jama_client/__about__.py
py_jama_client/__init__.py
py_jama_client/client.py
py_jama_client/constants.py
py_jama_client/exceptions.py
py_jama_client/helpers.py
py_jama_client/py.typed
py_jama_client/response.py
py_jama_client/apis/__init__.py
py_jama_client/apis/abstract_items_api.py
py_jama_client/apis/activities_api.py
py_jama_client/apis/attachments_api.py
py_jama_client/apis/baselines_api.py
py_jama_client/apis/filters_api.py
py_jama_client/apis/item_types_api.py
py_jama_client/apis/items_api.py
py_jama_client/apis/pick_list_options_api.py
py_jama_client/apis/pick_lists_api.py
py_jama_client/apis/projects_api.py
py_jama_client/apis/relationships_api.py
py_jama_client/apis/releases_api.py
py_jama_client/apis/tags_api.py
py_jama_client/apis/test_cycles_api.py
py_jama_client/apis/test_plans_api.py
py_jama_client/apis/test_runs_api.py
py_jama_client/apis/users_api.py
py_jama_client-0.4.2.dist-info/METADATA
py_jama_client-0.4.2.dist-info/WHEEL
py_jama_client-0.4.2.dist-info/licenses/LICENSE
py_jama_client-0.4.2.dist-info/RECORD
