Metadata-Version: 2.4
Name: py_jama_client
Version: 0.4.2
Summary: Python client library for Jama Connect
Project-URL: source, https://github.com/austinhallett/py_jama_client
Project-URL: issues, https://github.com/austinhallett/py_jama_client/issues
Author: Austin Hallett-Doughty
License-Expression: MIT
License-File: LICENSE
Classifier: Operating System :: OS Independent
Classifier: Programming Language :: Python :: 3
Requires-Python: >=3.11
Requires-Dist: anyio>=3.7.1
Requires-Dist: httpx>=0.24.1
Requires-Dist: python-jose>=3.3.0
Requires-Dist: requests>=2.31.0
Provides-Extra: test
Requires-Dist: black>=23.7.0; extra == 'test'
Requires-Dist: build>=1.0.0; extra == 'test'
Requires-Dist: flake8>=6.0.0; extra == 'test'
Requires-Dist: pytest-asyncio>=0.21.1; extra == 'test'
Requires-Dist: pytest-cov>=4.1.0; extra == 'test'
Requires-Dist: pytest-dotenv>=0.5.2; extra == 'test'
Requires-Dist: pytest>=7.4.0; extra == 'test'
